{
  "$schema": "https://developer.microsoft.com/json-schemas/spfx-build/package-solution.schema.json",
  "solution": {
    "name": "quick-poll-ace-client-side-solution",
    "id": "c0bc963e-e1ba-4c8d-a36c-8e3f54cb9ad2",
    "version": "1.0.0.0",
    "includeClientSideAssets": true,
    "skipFeatureDeployment": true,
    "isDomainIsolated": false,
    "developer": {
      "name": "",
      "websiteUrl": "",
      "privacyUrl": "",
      "termsOfUseUrl": "",
      "mpnId": "Undefined-1.14.0"
    },
    "metadata": {
      "shortDescription": {
        "default": "quick-poll-ace description"
      },
      "longDescription": {
        "default": "quick-poll-ace description"
      },
      "screenshotPaths": [],
      "videoUrl": "",
      "categories": []
    },
    "features": [
      {
        "title": "quick-poll-ace Feature",
        "description": "The feature that activates elements of the quick-poll-ace solution.",
        "id": "c452830d-8ad1-4dc6-b2f0-fc32b54f93db",
        "version": "1.0.0.0"
      }
    ],
    "webApiPermissionRequests": [
      {
        "resource": "Microsoft Graph",
        "scope": "Sites.ReadWrite.All"
      },
      {
        "resource": "Microsoft Graph",
        "scope": "User.Read.All"
      },
      {
        "resource": "Microsoft Graph",
        "scope": "User.ReadWrite.All"
      },
      {
        "resource": "Microsoft Graph",
        "scope": "Directory.Read.All"
      },
      {
        "resource": "Microsoft Graph",
        "scope": "Directory.ReadWrite.All"
      },
      {
        "resource": "Microsoft Graph",
        "scope": "Sites.Manage.All"
      }
    ]
  },
  "paths": {
    "zippedPackage": "solution/quick-poll-ace.sppkg"
  }
}
